dotalib/__init__.py
dotalib/utils.py
dotalib/core/__init__.py
dotalib/core/entities.py
dotalib/data/__init__.py
dotalib/data/heroes.py
dotalib/parse/__init__.py
dotalib/parse/base.py
dotalib/parse/cyberscore.py
dotalib/parse/dotabuff.py
dotalib/parse/hawk/__init__.py
dotalib/parse/hawk/livematches.py
dotalib/parse/hawk/match.py
dotalib/parse/hawk/odds.py
dotalib-0.0.5.dist-info/LICENSE
dotalib-0.0.5.dist-info/METADATA
dotalib-0.0.5.dist-info/WHEEL
dotalib-0.0.5.dist-info/top_level.txt
dotalib-0.0.5.dist-info/RECORD
