Metadata-Version: 2.1
Name: dotalib
Version: 0.0.5
Summary: dotalib
Author-email: deseg <deseg@gmail.com>
Classifier: Programming Language :: Python :: 3
Classifier: License :: OSI Approved :: MIT License
Classifier: Operating System :: OS Independent
Requires-Python: >=3.7
License-File: LICENSE
Requires-Dist: beautifulsoup4
